anchorpoint/__init__.py
anchorpoint/textselectors.py
anchorpoint/textsequences.py
anchorpoint-0.8.2.dist-info/METADATA
anchorpoint-0.8.2.dist-info/WHEEL
anchorpoint-0.8.2.dist-info/top_level.txt
anchorpoint-0.8.2.dist-info/RECORD
