Metadata-Version: 2.1
Name: anchorpoint
Version: 0.8.2
Summary: Text substring selectors for anchoring annotations
Home-page: https://github.com/mscarey/anchorpoint
Author: Matt Carey
Author-email: matt@authorityspoke.com
Project-URL: Bug Tracker, https://github.com/mscarey/anchorpoint/issues
Project-URL: Documentation, https://anchorpoint.readthedocs.io/en/latest/
Classifier: Development Status :: 4 - Beta
Classifier: License :: Free To Use But Restricted
Classifier: Programming Language :: Python :: 3.8
Classifier: Programming Language :: Python :: 3.9
Classifier: Programming Language :: Python :: 3.10
Classifier: Programming Language :: Python :: 3.11
Classifier: Programming Language :: Python :: 3.12
Classifier: Operating System :: OS Independent
Classifier: Natural Language :: English
Requires-Python: >=3.8
Requires-Dist: pydantic >=2.4.2
Requires-Dist: python-ranges >=1.2.2
